hotchocolate/__init__.py
hotchocolate/builders.py
hotchocolate/cli.py
hotchocolate/css.py
hotchocolate/logging.py
hotchocolate/markdown.py
hotchocolate/plugins.py
hotchocolate/readers.py
hotchocolate/settings.py
hotchocolate/settings.toml
hotchocolate/site.py
hotchocolate/templates.py
hotchocolate/utils.py
hotchocolate/writers.py
hotchocolate/style/article.scss
hotchocolate/style/aside.scss
hotchocolate/style/code.scss
hotchocolate/style/footer.scss
hotchocolate/style/main.scss
hotchocolate/style/pagination.scss
hotchocolate/style/pygments.scss
hotchocolate/styles/article.scss
hotchocolate/styles/aside.scss
hotchocolate/styles/code.scss
hotchocolate/styles/footer.scss
hotchocolate/styles/pagination.scss
hotchocolate/styles/pygments.scss
hotchocolate/styles/style.scss
hotchocolate/templates/archive.html
hotchocolate/templates/article.html
hotchocolate/templates/article_content.html
hotchocolate/templates/base.html
hotchocolate/templates/base_footer.html
hotchocolate/templates/base_head.html
hotchocolate/templates/base_header.html
hotchocolate/templates/index.html
hotchocolate/templates/page.html
hotchocolate/templates/pagination.html
hotchocolate/templates/post.html
hotchocolate/templates/post_content.html
hotchocolate-3.0.1.dist-info/DESCRIPTION.rst
hotchocolate-3.0.1.dist-info/METADATA
hotchocolate-3.0.1.dist-info/RECORD
hotchocolate-3.0.1.dist-info/WHEEL
hotchocolate-3.0.1.dist-info/entry_points.txt
hotchocolate-3.0.1.dist-info/metadata.json
hotchocolate-3.0.1.dist-info/top_level.txt
