Metadata-Version: 2.0
Name: hotchocolate
Version: 3.0.1
Summary: A static site generator designed for lightweight sites
Home-page: https://github.com/alexwlchan/hot-chocolate
Author: Alex Chan
Author-email: alex@alexwlchan.net
License: MIT
Platform: UNKNOWN
Classifier: Development Status :: 3 - Alpha
Classifier: Intended Audience :: Other Audience
Classifier: License :: OSI Approved :: MIT License
Classifier: Programming Language :: Python :: 3.6
Classifier: Programming Language :: Python :: 3 :: Only
Requires-Python: >=3.6
Requires-Dist: beautifulsoup4 (>=4.6.0,<5)
Requires-Dist: click (>=6.7,<7)
Requires-Dist: csscompressor (>=0.9.4,<1)
Requires-Dist: docker (<3,>=2.0.2)
Requires-Dist: feedgenerator (<2,>=1.9)
Requires-Dist: htmlmin (<0.2,>=0.1.10)
Requires-Dist: python-dateutil (>=2.6.0,<3)
Requires-Dist: Jinja2 (<3,>=2.9.5)
Requires-Dist: Markdown (<3,>=2.6.8)
Requires-Dist: mincss (>=0.11.2,<0.12)
Requires-Dist: Pygments (<3,>=2.2.0)
Requires-Dist: pyScss (>=1.3.5,<2)
Requires-Dist: toml (<1,>=0.9.2)
Requires-Dist: unidecode (<0.05,>=0.04.20)
